gaitutils/__init__.py
gaitutils/analysis.py
gaitutils/autoprocess.py
gaitutils/c3d.py
gaitutils/config.py
gaitutils/eclipse.py
gaitutils/emg.py
gaitutils/envutils.py
gaitutils/events.py
gaitutils/models.py
gaitutils/nexus.py
gaitutils/normaldata.py
gaitutils/numutils.py
gaitutils/read_data.py
gaitutils/sessionutils.py
gaitutils/stats.py
gaitutils/timedist.py
gaitutils/trial.py
gaitutils/utils.py
gaitutils/videos.py
gaitutils/assets/12_col.css
gaitutils/data/default.cfg
gaitutils/data/emg_normaldata.json
gaitutils/data/normal.gcd
gaitutils/data/timedist_normaldata.json
gaitutils/gui/__init__.py
gaitutils/gui/_gaitmenu.py
gaitutils/gui/_tardieu.py
gaitutils/gui/_windows.py
gaitutils/gui/add_session_dialog.ui
gaitutils/gui/gaitmenu.py
gaitutils/gui/gaitmenu.ui
gaitutils/gui/nicelistwidget_plugin.py
gaitutils/gui/pdf_report_dialog.ui
gaitutils/gui/pdf_report_dialog_comparison.ui
gaitutils/gui/qt_dialogs.py
gaitutils/gui/qt_widgets.py
gaitutils/gui/sessions.ui
gaitutils/gui/tardieu.ui
gaitutils/gui/tardieu_filter_dialog.ui
gaitutils/gui/tardieu_help_dialog.ui
gaitutils/gui/tardieu_load_dialog.ui
gaitutils/gui/web_report_dialog.ui
gaitutils/gui/web_report_info.ui
gaitutils/report/__init__.py
gaitutils/report/pdf.py
gaitutils/report/text.py
gaitutils/report/translations.py
gaitutils/report/web.py
gaitutils/thirdparty/__init__.py
gaitutils/thirdparty/ffmpeg2theora-0.30.tar.bz2
gaitutils/thirdparty/ffmpeg2theora.exe
gaitutils/thirdparty/btk/__init__.py
gaitutils/thirdparty/btk/_btk.pyd
gaitutils/viz/__init__.py
gaitutils/viz/console.py
gaitutils/viz/layouts.py
gaitutils/viz/plot_common.py
gaitutils/viz/plot_matplotlib.py
gaitutils/viz/plot_misc.py
gaitutils/viz/plot_plotly.py
gaitutils/viz/plots.py
gaitutils/viz/timedist.py
gaitutils-0.13.9.dist-info/LICENSE
gaitutils-0.13.9.dist-info/METADATA
gaitutils-0.13.9.dist-info/WHEEL
gaitutils-0.13.9.dist-info/entry_points.txt
gaitutils-0.13.9.dist-info/top_level.txt
gaitutils-0.13.9.dist-info/RECORD
