Metadata-Version: 2.1
Name: gaitutils
Version: 0.13.9
Summary: Utilities for processing and plotting gait data
Home-page: https://github.com/jjnurminen/gaitutils
Author: Jussi Nurminen
Author-email: jnu@iki.fi
License: GPLv3
Platform: UNKNOWN
License-File: LICENSE
